ddcompiler/__init__.py
ddcompiler/lexer.py
ddcompiler/parser.py
ddcompiler/token.py
ddcompiler-1.1.0.dist-info/LICENSE
ddcompiler-1.1.0.dist-info/WHEEL
ddcompiler-1.1.0.dist-info/METADATA
ddcompiler-1.1.0.dist-info/RECORD
