Metadata-Version: 2.1
Name: ddcompiler
Version: 1.1.0
Summary: Interpreter for evaluating expressions used in AutomationEdge AIStudio dialog designer
Home-page: https://automationedge.com
License: MIT
Keywords: interpreter, compiler, lexer, parse tree
Author: Yogesh Ketkar
Author-email: yogesh.ketkar@automationedge.com
Requires-Python: >=3.0,<4.0
Classifier: License :: OSI Approved :: MIT License
Classifier: Programming Language :: Python :: 3
Classifier: Programming Language :: Python :: 3.10
Classifier: Programming Language :: Python :: 3.4
Classifier: Programming Language :: Python :: 3.5
Classifier: Programming Language :: Python :: 3.6
Classifier: Programming Language :: Python :: 3.7
Classifier: Programming Language :: Python :: 3.8
Classifier: Programming Language :: Python :: 3.9
Project-URL: Repository, http://bitbucket.org/yovyom/ddcompiler
